onetjobsInf/OnetWebService.py
onetjobsInf/__init__.py
onetjobsInf/bfs_abilities_search.py
onetjobsInf/bfs_job_abilities_graph.py
onetjobsInf/bfs_job_knowledge_graph.py
onetjobsInf/bfs_job_skills_graph.py
onetjobsInf/bfs_knowledge_search.py
onetjobsInf/bfs_skills_search.py
onetjobsInf/onet_credentials.py
onetjobsInf/onet_keyword_search.py
onetjobsInf/pca_request_data.py
onetjobsInf/pca_run.py
onetjobsInf/pca_scaling.py
onetjobsInf/vis_app.py
onetjobsInf/vis_call_elements.py
onetjobsInf/vis_call_labels.py
onetjobsInf/vis_download_files.py
onetjobsInf/vis_layout.py
onetjobsInf/src_data/Occupation Data.txt
onetjobsInf/src_data/element_name_dict.json
onetjobsInf/test/__init__.py
onetjobsInf/test/test_BFS_search.py
onetjobsInf/test/test_abilities_download.py
onetjobsInf/test/test_linalg_skills.py
onetjobsinf-0.1.30.dist-info/licenses/LICENSE
onetjobsinf-0.1.30.dist-info/METADATA
onetjobsinf-0.1.30.dist-info/WHEEL
onetjobsinf-0.1.30.dist-info/top_level.txt
onetjobsinf-0.1.30.dist-info/RECORD
