Metadata-Version: 2.4
Name: onetjobsInf
Version: 0.1.30
Summary: A python package for contrasting and comparing jobs based on skills, knowledge, and abilities, as obtained from the O*NET Database.
Author-email: "P. Nevins" <pnevins@fas.harvard.edu>, "M. Carbonneau" <mcarbonneau@g.harvard.edu>, "H. Jin" <hannahjin@g.harvard.edu>
License: MIT
Project-URL: Homepage, https://pypi.org/project/onetjobsSKA/
Project-URL: Dashboard, https://bst236-onetcompare-a23cabb5a2d4.herokuapp.com/
Keywords: PCA,breadth-first search,job comparison,radar plots,O*NET
Classifier: Programming Language :: Python :: 3
Classifier: License :: OSI Approved :: MIT License
Classifier: Operating System :: OS Independent
Requires-Python: ==3.7
License-File: LICENSE
Requires-Dist: dash==2.11.1
Requires-Dist: pandas>=1.0.0
Requires-Dist: plotly>=5.0.0
Requires-Dist: requests>=2.0.0
Requires-Dist: werkzeug==2.0.3
Requires-Dist: scipy>=1.11.0
Requires-Dist: matplotlib>=3.7.0
Requires-Dist: numpy>=1.24.0
Dynamic: license-file
